pydungeoncrawl/__init__.py
pydungeoncrawl/_level.py
pydungeoncrawl/armor.py
pydungeoncrawl/bosses.py
pydungeoncrawl/buffs.py
pydungeoncrawl/debuffs.py
pydungeoncrawl/heroes.py
pydungeoncrawl/levels.py
pydungeoncrawl/weapons.py
pydungeoncrawl/entities/__init__.py
pydungeoncrawl/entities/board.py
pydungeoncrawl/entities/characters.py
pydungeoncrawl/entities/effects.py
pydungeoncrawl/entities/equipment.py
pydungeoncrawl/entities/monster.py
pydungeoncrawl/entities/pawn.py
pydungeoncrawl/utilities/__init__.py
pydungeoncrawl/utilities/analysis.py
pydungeoncrawl/utilities/location.py
pydungeoncrawl/utilities/map_making.py
pydungeoncrawl/utilities/base_maps/__init__.py
pydungeoncrawl/utilities/base_maps/advanced_movement.json
pydungeoncrawl/utilities/base_maps/beach_party.json
pydungeoncrawl/utilities/base_maps/cabin_at_the_lake.json
pydungeoncrawl/utilities/base_maps/forest_path.json
pydungeoncrawl/utilities/base_maps/higher_ground.json
pydungeoncrawl/utilities/base_maps/lava_cave.json
pydungeoncrawl/utilities/base_maps/pathtest.json
pydungeoncrawl/utilities/base_maps/river_ford.json
pydungeoncrawl/utilities/base_maps/simple_map.json
pydungeoncrawl-0.1.9.dist-info/LICENSE
pydungeoncrawl-0.1.9.dist-info/METADATA
pydungeoncrawl-0.1.9.dist-info/WHEEL
pydungeoncrawl-0.1.9.dist-info/top_level.txt
pydungeoncrawl-0.1.9.dist-info/RECORD
